invisibleroads_macros_disk/__init__.py
invisibleroads_macros_disk/constants.py
invisibleroads_macros_disk/exceptions.py
invisibleroads_macros_disk/operations.py
invisibleroads_macros_disk/resolutions.py
invisibleroads_macros_disk-1.3.0.dist-info/METADATA
invisibleroads_macros_disk-1.3.0.dist-info/WHEEL
invisibleroads_macros_disk-1.3.0.dist-info/top_level.txt
invisibleroads_macros_disk-1.3.0.dist-info/zip-safe
invisibleroads_macros_disk-1.3.0.dist-info/RECORD
