Metadata-Version: 2.1
Name: invisibleroads-macros-disk
Version: 1.3.0
Summary: Shortcut functions for disk operations
Home-page: https://github.com/invisibleroads/invisibleroads-macros-disk
Author: Roy Hyunjin Han
Author-email: rhh@crosscompute.com
Keywords: invisibleroads
Classifier: Programming Language :: Python
Classifier: License :: OSI Approved :: MIT License
Requires-Python: >=3.9
Requires-Dist: invisibleroads-macros-security (>=1.0.3)
Requires-Dist: platformdirs
Provides-Extra: test
Requires-Dist: pytest ; extra == 'test'
Requires-Dist: pytest-cov ; extra == 'test'
